README.rst
setup.cfg
setup.py
aimdvcli/__init__.py
aimdvcli/aimdvcli.py
aimdvcli.egg-info/PKG-INFO
aimdvcli.egg-info/SOURCES.txt
aimdvcli.egg-info/dependency_links.txt
aimdvcli.egg-info/entry_points.txt
aimdvcli.egg-info/requires.txt
aimdvcli.egg-info/top_level.txt
aimdvcli/audio/__init__.py
aimdvcli/audio/convert.py