Metadata-Version: 1.1
Name: aimdvcli
Version: 0.1.2
Summary: AIMDV Client
Home-page: http://www.sns.co.kr/
Author: Semicon Networks
Author-email: hansroh@gmail.com
License: MIT
Download-URL: https://pypi.python.org/pypi/aimdvcli
Platform: posix
Platform: nt
Classifier: License :: OSI Approved :: MIT License
Classifier: Development Status :: 3 - Alpha
Classifier: Topic :: Database
Classifier: Intended Audience :: Developers
Classifier: Programming Language :: Python
Classifier: Programming Language :: Python :: 3
